[
{"text": "Strona główna - Uniwersytet Jagielloński"},
{"text": "facebook"},
{"text": "x"},
{"text": "Biuletyn Informacji Publicznej - Uniwersytet Jagielloński"},
{"text": "Dydaktyka w Collegium Medicum - Uniwersytet Jagielloński"},
{"text": "facebook"},
{"text": "x"},
{"text": "Deklaracje dostępności - Uniwersytet Jagielloński"},
{"text": "Muzea - Uniwersytet Jagielloński"},
{"text": "facebook"},
{"text": "x"},
{"text": "Domy i hotele - Uniwersytet Jagielloński"},
{"text": "facebook"},
{"text": "x"},
{"text": "Szkoły Doktorskie - Uniwersytet Jagielloński"},
{"text": "Centrum Wsparcia Dydaktyki - Centrum Wsparcia Dydaktyki - Uniwersytet Jagielloński"},
{"text": "Kalendarz akademicki - Sprawy studentów i doktorantów - Uniwersytet Jagielloński"},
{"text": "Biblioteki i archiwum - Uniwersytet Jagielloński"},
{"text": "facebook"},
{"text": "x"},
{"text": "facebook"},
{"text": "x"},
{"text": "Dydaktyka - Uniwersytet Jagielloński"},
{"text": "facebook"},
{"text": "x"},
{"text": "Administracja - Uniwersytet Jagielloński"},
{"text": "facebook"},
{"text": "x"},
{"text": "Regulamin organizacyjny - Uniwersytet Jagielloński"},
{"text": "facebook"},
{"text": "x"},
{"text": "Uchwały Rady Uczelni - Rada Uczelni - Uniwersytet Jagielloński"},
{"text": "Artes Liberales - Sprawy studentów i doktorantów - Uniwersytet Jagielloński"},
{"text": "Oferta dydaktyczna Uniwersytetu Jagiellońskiego - Oferta dydaktyczna UJ - Uniwersytet Jagielloński"},
{"text": "facebook"},
{"text": "x"},
{"text": "Jednostki poza- i międzywydziałowe - Uniwersytet Jagielloński"},
{"text": "facebook"},
{"text": "x"},
{"text": "Stasin Niemen Historia - Uniwersytet Jagielloński"},
{"text": "facebook"},
{"text": "x"},
{"text": "Muzeum Anatomopatologiczne - Uniwersytet Jagielloński"},
{"text": "facebook"},
{"text": "x"},
{"text": "Strona główna - Jakość kształcenia - Uniwersytet Jagielloński"},
{"text": "facebook"},
{"text": "Muzeum Historii Medycyny UJ CM - Uniwersytet Jagielloński"},
{"text": "facebook"},
{"text": "x"},
{"text": "Uniwersytet Jagielloński - Collegium Medicum"},
{"text": "School of Medicine in English"},
{"text": "Deklaracje dostępności - Uniwersytet Jagielloński"},
{"text": "Pion Zastępcy Kanclerza ds. administrowania nieruchomościami - Uniwersytet Jagielloński"},
{"text": "facebook"},
{"text": "x"},
{"text": "Katedra i Zakład Anatomii"},
{"text": "Sign In"},
{"text": "Dwór w Modlnicy – UJinn.pl"},
{"text": "Pion Kanclerza - Uniwersytet Jagielloński"},
{"text": "facebook"},
{"text": "x"},
{"text": "Sign In"},
{"text": "Sign In"},
{"text": "Domy Pracy Twórczej - Dział Świadczeń Socjalnych - Centrum Spraw Osobowych"},
{"text": " Strona główna - International PhD studies in medical sciences Jagiellonian University Medical College, Faculty of Medicine Uniwersytetu Jagiellońskiego"},
{"text": "Muzeum Ogrodu Botanicznego - Ogród Botaniczny - Uniwersytet Jagielloński"},
{"text": "List of websites - Accessibility Statements - Jagiellonian University"},
{"text": "Sign In"},
{"text": "Sign In"},
{"text": "Sign In"},
{"text": "Centrum Językowe UJ CM"},
{"text": "Dział Administracji Kampusu 600-lecia Odnowienia UJ - Uniwersytet Jagielloński"},
{"text": "facebook"},
{"text": "x"},
{"text": "Kontakt – UJinn.pl"},
{"text": "Biuro Zastępcy Kanclerza ds. administrowania nieruchomościami - Uniwersytet Jagielloński"},
{"text": "facebook"},
{"text": "x"},
{"text": "Galeria – UJinn.pl"},
{"text": "School of Medicine in English"},
{"text": "Strona główna - DAdN - Uniwersytet Jagielloński"},
{"text": "Contact - Accessibility Statements - Jagiellonian University"},
{"text": "zgłoszenia - Accessibility - Jagiellonian University"},
{"text": "zgłoszenia - Dostępność - Uniwersytet Jagielloński"},
{"text": "Deklaracja dostępności – UJinn.pl"},
{"text": "CEP - Centrum Edukacji Przyrodniczej - Uniwersytet Jagielloński"},
{"text": "facebook"},
{"text": "Dział Zamówień Publicznych - Uniwersytet Jagielloński"},
{"text": "Pigoniówka – UJinn.pl"},
{"text": "Floriańska 49 – UJinn.pl"},
{"text": "Redakcja strony www UJ CM - Uniwersytet Jagielloński - Collegium Medicum"},
{"text": "Narzędzia ułatwień dostępu"},
{"text": "Zwieksz tekst"},
{"text": "Zmniejsz tekst"},
{"text": "Skala szarości"},
{"text": "Wysoki kontrast"},
{"text": "Negatywny kontrast"},
{"text": "Jasne tło"},
{"text": "Podkrerślone linki"},
{"text": "Czytelna czcionka"},
{"text": "Reset"},
{"text": "Galeria – UJinn.pl"},
{"text": "Centrum Językowe UJ CM"},
{"text": "Współpraca z otoczeniem - Uniwersytet Jagielloński"},
{"text": "facebook"},
{"text": "x"},
{"text": "Po Prostu Nauka"},
{"text": "Współpraca Collegium Medicum - Uniwersytet Jagielloński"},
{"text": "facebook"},
{"text": "x"},
{"text": "Kontakt - Deklaracje dostępności - Uniwersytet Jagielloński"},
{"text": "o dostępności - Dostępność - Uniwersytet Jagielloński"},
{"text": "List of websites - Accessibility Statements - Jagiellonian University"},
{"text": "Sieci współpracy - Uniwersytet Jagielloński"},
{"text": "facebook"},
{"text": "x"},
{"text": "Deklaracja dostępności – UJinn.pl"},
{"text": "List of websites - Accessibility Statements - Jagiellonian University"},
{"text": "Kontakt – UJinn.pl"},
{"text": "Galeria – UJinn.pl"},
{"text": "Lista jednostek administracyjnych - Uniwersytet Jagielloński"},
{"text": "facebook"},
{"text": "x"},
{"text": "Sign In"},
{"text": "O nas – UJinn.pl"},
{"text": "Oferta – UJinn.pl"},
{"text": "Zgłoszone witryny - Deklaracje dostępności - Uniwersytet Jagielloński"},
{"text": "Rekrutacja - Uniwersytet Jagielloński - Collegium Medicum"},
{"text": "Narzędzia ułatwień dostępu"},
{"text": "Zwieksz tekst"},
{"text": "Zmniejsz tekst"},
{"text": "Skala szarości"},
{"text": "Wysoki kontrast"},
{"text": "Negatywny kontrast"},
{"text": "Jasne tło"},
{"text": "Podkrerślone linki"},
{"text": "Czytelna czcionka"},
{"text": "Reset"},
{"text": "Zgłoszone aplikacje - Deklaracje dostępności - Uniwersytet Jagielloński"},
{"text": "Po Prostu Nauka"},
{"text": "Strona główna - Uniwersytet Jagielloński"},
{"text": "facebook"},
{"text": "x"},
{"text": "Moje wpisy - Deklaracje dostępności - Uniwersytet Jagielloński"},
{"text": "o dostępności - Accessibility - Jagiellonian University"},
{"text": "Rejestr aplikacji - Deklaracje dostępności - Uniwersytet Jagielloński"},
{"text": "Rejestr witryn - Deklaracje dostępności - Uniwersytet Jagielloński"},
{"text": "Deklaracje dostępności - Uniwersytet Jagielloński"},
{"text": "Kontakt – UJinn.pl"},
{"text": "Galeria – UJinn.pl"},
{"text": "HR Excellence in Research - International Visitors' Office - Jagiellonian University"},
{"text": "facebook"},
{"text": "x"},
{"text": "Sign In"},
{"text": "Sign In"},
{"text": "Sign In"},
{"text": "o dostępności - Dostępność - Uniwersytet Jagielloński"},
{"text": "Deklaracje dostępności - Uniwersytet Jagielloński"},
{"text": "Sign In"},
{"text": "List of websites - Accessibility Statements - Jagiellonian University"},
{"text": "Sign In"},
{"text": "Sign In"},
{"text": "Sign In"},
{"text": "Biuro Prorektora ds. Badań Naukowych i Funduszy Strukturalnych - Uniwersytet Jagielloński"},
{"text": "facebook"},
{"text": "x"},
{"text": "Sign In"},
{"text": "Sign In"},
{"text": "Deklaracje dostępności - Uniwersytet Jagielloński"},
{"text": "List of websites - Accessibility Statements - Jagiellonian University"},
{"text": "Kwestura"},
{"text": "O nas – UJinn.pl"},
{"text": "Oferta – UJinn.pl"},
{"text": "o dostępności - Dostępność - Uniwersytet Jagielloński"},
{"text": "Budynek Centrum Edukacji Przyrodniczej - Dział Administracji Kampusu 600-lecia Odnowienia UJ - Uniwersytet Jagielloński"},
{"text": "Uniwersytecki Klub Sportowy - Uniwersytet Jagielloński"},
{"text": "facebook"},
{"text": "x"},
{"text": "Sign In"},
{"text": "O budynku na Czapskich - Dostępność - Uniwersytet Jagielloński"},
{"text": "Sign In"},
{"text": "List of websites - Accessibility Statements - Jagiellonian University"},
{"text": "Sign In"},
{"text": "List of websites - Accessibility Statements - Jagiellonian University"},
{"text": "kontakt - Dostępność - Uniwersytet Jagielloński"},
{"text": "Kwestura"},
{"text": "Sign In"},
{"text": "ludzie dostępności - Dostępność - Uniwersytet Jagielloński"},
{"text": "Kwestura"},
{"text": "Deklaracje dostępności - Uniwersytet Jagielloński"},
{"text": "Kwestura"},
{"text": "Panele eksperckie - Dostępność - Uniwersytet Jagielloński"},
{"text": "Deklaracje dostępności - Uniwersytet Jagielloński"},
{"text": "podstawa zapewnienia dostępności - Dostępność - Uniwersytet Jagielloński"},
{"text": "KS Uniwersytet Jagielloński (@uj_jagiellonki) • Instagram photos and videos"},
{"text": "International Visitors' Office - International Visitors' Office - Jagiellonian University"},
{"text": "facebook"},
{"text": "x"}
]